aioacme/__init__.py
aioacme/_client.py
aioacme/_directories.py
aioacme/_exceptions.py
aioacme/_jwk.py
aioacme/_jws.py
aioacme/_models.py
aioacme/_types.py
aioacme/_utils.py
aioacme/_version.py
aioacme/py.typed
aioacme-0.5.0.dist-info/LICENSE
aioacme-0.5.0.dist-info/METADATA
aioacme-0.5.0.dist-info/WHEEL
aioacme-0.5.0.dist-info/top_level.txt
aioacme-0.5.0.dist-info/RECORD
