Metadata-Version: 2.1
Name: aioacme
Version: 0.5.0
Summary: Async ACME client implementation
Author-email: Timofei Kukushkin <tima@kukushkin.me>
License: MIT License
Project-URL: Homepage, https://github.com/tkukushkin/aioacme
Project-URL: Repository, https://github.com/tkukushkin/aioacme.git
Project-URL: Issues, https://github.com/tkukushkin/aioacme/issues
Project-URL: Documentation, https://aioacme.readthedocs.io/stable
Project-URL: Changelog, https://github.com/tkukushkin/aioacme/releases
Classifier: Development Status :: 4 - Beta
Classifier: Intended Audience :: Developers
Classifier: License :: OSI Approved :: MIT License
Classifier: Operating System :: OS Independent
Classifier: Programming Language :: Python :: 3
Classifier: Programming Language :: Python :: 3.10
Classifier: Programming Language :: Python :: 3.11
Classifier: Programming Language :: Python :: 3.12
Classifier: Topic :: Software Development :: Libraries :: Python Modules
Classifier: Framework :: AsyncIO
Classifier: Framework :: Trio
Requires-Python: >=3.10
License-File: LICENSE
Requires-Dist: anyio
Requires-Dist: httpx
Requires-Dist: cryptography
Requires-Dist: orjson
Requires-Dist: serpyco-rs
Requires-Dist: python-dateutil
Requires-Dist: typing-extensions ; python_version < "3.11"
